mm_fitting/__init__.py
mm_fitting/methods.py
mm_fitting-1.1.dist-info/LICENSE
mm_fitting-1.1.dist-info/METADATA
mm_fitting-1.1.dist-info/WHEEL
mm_fitting-1.1.dist-info/top_level.txt
mm_fitting-1.1.dist-info/RECORD
