Metadata-Version: 2.1
Name: mm-fitting
Version: 1.1
Summary: Methods to compute Michaelis-Menten equation parameters and statistics.
Author-email: António Ferreira <ferreiae@gmail.com>
License: MIT License
Keywords: Michaelis-Menten equation,parameter estimation
Classifier: Development Status :: 3 - Alpha
Classifier: Intended Audience :: Education
Classifier: Intended Audience :: Science/Research
Classifier: License :: OSI Approved :: BSD License
Classifier: Natural Language :: English
Classifier: Operating System :: OS Independent
Classifier: Programming Language :: Python
Classifier: Programming Language :: Python :: 3
Classifier: Programming Language :: Python :: 3.9
Classifier: Programming Language :: Python :: 3.10
Classifier: Topic :: Scientific/Engineering :: Chemistry
Classifier: Topic :: Scientific/Engineering :: Physics
Requires-Python: >=3.9
License-File: LICENSE
Requires-Dist: numpy >=1.1
